Zerg
Zerg_Drone
Zerg_Drone
Zerg_Drone
Zerg_Drone
Zerg_Overlord
Zerg_Drone
Zerg_Drone
Zerg_Drone
Zerg_Drone
Zerg_Hatchery
Zerg_Spawning_Pool
Zerg_Drone
Zerg_Drone
Zerg_Hatchery
Zerg_Extractor
Zerg_Drone
Zerg_Drone
Zerg_Drone
Zerg_Overlord
Zerg_Lair
Zerg_Extractor
Zerg_Drone
Zerg_Drone
Zerg_Zergling
Zerg_Zergling
Zerg_Zergling
Zerg_Drone
Zerg_Drone
Zerg_Drone
Zerg_Drone
Zerg_Overlord
Zerg_Drone
Zerg_Overlord
Zerg_Drone
Zerg_Overlord
Zerg_Spire
Zerg_Drone
Zerg_Drone
Zerg_Drone
Zerg_Drone
Zerg_Drone
Zerg_Mutalisk
Zerg_Mutalisk
Zerg_Mutalisk
Zerg_Mutalisk
Zerg_Mutalisk
Zerg_Mutalisk
Zerg_Mutalisk
Zerg_Mutalisk
Zerg_Mutalisk
Zerg_Mutalisk
Zerg_Mutalisk
Zerg_Mutalisk